<?xml version="1.0" encoding="UTF-8"?>
<dataset xmlns="urn:pangaea.de:dataportals" xmlns:dc="http://purl.org/dc/elements/1.1/" xmlns:xsi="http://www.w3.org/2001/XMLSchema-instance"><dc:title>Basic measurements of radiation at station Billings (2005-12)</dc:title><dc:creator>Long, Charles</dc:creator><principalInvestigator>Long, Charles</principalInvestigator><dc:source>Argonne National Laboratory</dc:source><dc:publisher>PANGAEA</dc:publisher><dataCenter>PANGAEA: Data Publisher for Earth &amp; Environmental Science</dataCenter><dc:date>2009-07-03</dc:date><dc:type>Dataset</dc:type><dc:format>text/tab-separated-values, 174159 data points</dc:format><dc:identifier>https://doi.org/10.1594/PANGAEA.723792</dc:identifier><dc:language>en</dc:language><dc:rights>Access constraints: access rights needed</dc:rights><dc:relation>Long, Charles (2009): BSRN Station-to-archive file for station Billings (2005-12). ftp://ftp.bsrn.awi.de/bil/bil1205.dat.gz</dc:relation><dc:subject type="parameter" xsi:type="SubjectType">DATE/TIME</dc:subject><dc:subject type="parameter" xsi:type="SubjectType">HEIGHT above ground</dc:subject><dc:subject type="parameter" xsi:type="SubjectType">Short-wave downward (GLOBAL) radiation</dc:subject><dc:subject type="parameter" xsi:type="SubjectType">Direct radiation</dc:subject><dc:subject type="parameter" xsi:type="SubjectType">Diffuse radiation</dc:subject><dc:subject type="parameter" xsi:type="SubjectType">Long-wave downward radiation</dc:subject><dc:subject type="method" xsi:type="SubjectType">Pyranometer, Eppley, PSP, SN 30668F3, WRMC No. 27049</dc:subject><dc:subject type="method" xsi:type="SubjectType">Pyrheliometer, Eppley, NIP, SN 29850E6, WRMC No. 27571</dc:subject><dc:subject type="method" xsi:type="SubjectType">Pyranometer, Eppley, 8-48, SN 32972, WRMC No. 27705</dc:subject><dc:subject type="method" xsi:type="SubjectType">Pyrgeometer, Eppley, PIR, SN 30357F3, WRMC No. 27432</dc:subject><dc:subject type="project" xsi:type="SubjectType">BSRN: Baseline Surface Radiation Network</dc:subject><dc:subject type="sensor" xsi:type="SubjectType">Monitoring station</dc:subject><dc:subject type="sensor" xsi:type="SubjectType">MONS</dc:subject><dc:subject type="feature" xsi:type="SubjectType">BIL</dc:subject><dc:subject type="feature" xsi:type="SubjectType">Billings</dc:subject><dc:subject type="feature" xsi:type="SubjectType">WCRP/GEWEX</dc:subject><dc:subject type="pangaea-tech-keyword" xsi:type="SubjectType">citable</dc:subject><dc:subject type="pangaea-tech-keyword" xsi:type="SubjectType">author31662</dc:subject><dc:subject type="pangaea-tech-keyword" xsi:type="SubjectType">campaign32853</dc:subject><dc:subject type="pangaea-tech-keyword" xsi:type="SubjectType">event2536899</dc:subject><dc:subject type="pangaea-tech-keyword" xsi:type="SubjectType">geocode1599</dc:subject><dc:subject type="pangaea-tech-keyword" xsi:type="SubjectType">geocode1600</dc:subject><dc:subject type="pangaea-tech-keyword" xsi:type="SubjectType">geocode1601</dc:subject><dc:subject type="pangaea-tech-keyword" xsi:type="SubjectType">geocode56349</dc:subject><dc:subject type="pangaea-tech-keyword" xsi:type="SubjectType">geocode8128</dc:subject><dc:subject type="pangaea-tech-keyword" xsi:type="SubjectType">inst32</dc:subject><dc:subject type="pangaea-tech-keyword" xsi:type="SubjectType">method11312</dc:subject><dc:subject type="pangaea-tech-keyword" xsi:type="SubjectType">method5500</dc:subject><dc:subject type="pangaea-tech-keyword" xsi:type="SubjectType">method5752</dc:subject><dc:subject type="pangaea-tech-keyword" xsi:type="SubjectType">method5878</dc:subject><dc:subject type="pangaea-tech-keyword" xsi:type="SubjectType">method6012</dc:subject><dc:subject type="pangaea-tech-keyword" xsi:type="SubjectType">param31460</dc:subject><dc:subject type="pangaea-tech-keyword" xsi:type="SubjectType">param45293</dc:subject><dc:subject type="pangaea-tech-keyword" xsi:type="SubjectType">param45294</dc:subject><dc:subject type="pangaea-tech-keyword" xsi:type="SubjectType">param45298</dc:subject><dc:subject type="pangaea-tech-keyword" xsi:type="SubjectType">pi31662</dc:subject><dc:subject type="pangaea-tech-keyword" xsi:type="SubjectType">project4094</dc:subject><dc:subject type="pangaea-tech-keyword" xsi:type="SubjectType">ref48056</dc:subject><dc:subject type="pangaea-tech-keyword" xsi:type="SubjectType">sourceinst2876</dc:subject><dc:subject type="pangaea-tech-keyword" xsi:type="SubjectType">term1073288</dc:subject><dc:subject type="pangaea-tech-keyword" xsi:type="SubjectType">term26751</dc:subject><dc:subject type="pangaea-tech-keyword" xsi:type="SubjectType">term43863</dc:subject><dc:subject type="pangaea-tech-keyword" xsi:type="SubjectType">term43923</dc:subject><dc:subject type="pangaea-tech-keyword" xsi:type="SubjectType">term43975</dc:subject><dc:subject type="pangaea-tech-keyword" xsi:type="SubjectType">term48981</dc:subject><dc:subject type="pangaea-tech-keyword" xsi:type="SubjectType">topotype8</dc:subject><dc:coverage xsi:type="CoverageType"><northBoundLatitude>36.605</northBoundLatitude><westBoundLongitude>-97.516</westBoundLongitude><southBoundLatitude>36.605</southBoundLatitude><eastBoundLongitude>-97.516</eastBoundLongitude><location>Oklahoma, United States of America</location><minElevation>2.0 m (HEIGHT above ground)</minElevation><maxElevation>2.0 m (HEIGHT above ground)</maxElevation><startDate>2005-12-01</startDate><endDate>2005-12-31</endDate></dc:coverage><linkage type="metadata">https://doi.pangaea.de/10.1594/PANGAEA.723792</linkage><linkage accessRestricted="true" type="data">https://doi.pangaea.de/10.1594/PANGAEA.723792?format=textfile</linkage><additionalContent>BSRN station no: 28; Surface type: grass; Topography type: flat, rural; Station scientist: Laura Riihimaki (laura.riihimaki@noaa.gov)</additionalContent></dataset>